<?xml version="1.0" encoding="UTF-8"?>
<img>
  <blog1>
    <seo>
      <es></es>
      <en></en>
      <de></de>
    </seo>
  </blog1>
  <blog_footer>
    <seo>
      <es></es>
      <en></en>
      <de></de>
    </seo>
  </blog_footer>
  <facebook1>
    <seo>
      <es></es>
      <en></en>
      <de></de>
    </seo>
  </facebook1>
  <facebook_footer>
    <seo>
      <es></es>
      <en></en>
      <de></de>
    </seo>
  </facebook_footer>
  <lock>
    <seo>
      <es></es>
      <en></en>
      <de></de>
    </seo>
  </lock>
  <mail>
    <seo>
      <es></es>
      <en></en>
      <de></de>
    </seo>
  </mail>
  <panel>
    <seo>
      <es></es>
      <en></en>
      <de></de>
    </seo>
  </panel>
  <phone>
    <seo>
      <es></es>
      <en></en>
      <de></de>
    </seo>
  </phone>
  <pin>
    <seo>
      <es></es>
      <en></en>
      <de></de>
    </seo>
  </pin>
  <skype>
    <seo>
      <es></es>
      <en></en>
      <de></de>
    </seo>
  </skype>
  <twitter1>
    <seo>
      <es></es>
      <en></en>
      <de></de>
    </seo>
  </twitter1>
  <twitter_footer>
    <seo>
      <es></es>
      <en></en>
      <de></de>
    </seo>
  </twitter_footer>
  <youtube>
    <seo>
      <es></es>
      <en></en>
      <de></de>
    </seo>
  </youtube>
  <youtube_footer>
    <seo>
      <es></es>
      <en></en>
      <de></de>
    </seo>
  </youtube_footer>
</img>
